pycord/__init__.py
pycord/video_reader.py
pycord-0.1.0.dist-info/LICENSE
pycord-0.1.0.dist-info/METADATA
pycord-0.1.0.dist-info/WHEEL
pycord-0.1.0.dist-info/top_level.txt
pycord-0.1.0.dist-info/RECORD
